{
  "id": 689,
  "name": "Bánh Tráng Cô Thư",
  "logo": "https://cdn.f99.link/groupbuy-images/35e9ca06-ff76-415d-ba00-6d253157b4b9.jpg",
  "banner": "https://i.imgur.com/Y09Ptqu.png",
  "type": "Retailer",
  "businessId": null,
  "phoneNumber": null,
  "description": "-\tCHUYÊN BÁNH TRÁNG SATE TỎI + ỚT RYM VỊ ĐỘC QUYỀN TÂY NINH LOẠI 1 \n-\tKHÔNG QUA TRUNG GIAN! - HÀNG E CÓ SẴN SLL",
  "headQuarter": "10/28 Tân Quý, Tân Quý, Tân Phú, Hồ Chí Minh",
  "email": "Thupham771@gmail.com",
  "totalProduct": 0,
  "isNew": false,
  "isAutoOrderConfirmation": true,
  "rating": 4.2,
  "availableTime": {
    "openTime": "08:00",
    "closeTime": "19:30",
    "holidays": [
      {
        "name": "Tet Holiday",
        "startHolidayTime": "2022-01-29T17:00:00",
        "endHolidayTime": "2022-02-07T00:00:00"
      }
    ]
  },
  "warehouse": null,
  "warehouses": null,
  "createdTime": "0001-01-01T00:00:00",
  "isPublished": true,
  "note": null,
  "isF99Shop": null,
  "onStore": false,
  "totalVote": 5
}