{
  "id": 991,
  "name": "VUA DỪA XIÊM BẾN TRE – 290 ĐƯỜNG LÁNG",
  "logo": "https://images.f99.com.vn/groupbuy-images/6267514b-8d2a-4ad8-b3c7-7bb0be6690cd.png",
  "banner": "https://i.imgur.com/Y09Ptqu.png",
  "type": "Retailer",
  "businessId": null,
  "phoneNumber": null,
  "description": "290 Đường Láng, Phường Thịnh Quang, Q. Đống Đa, Hà Nội",
  "headQuarter": "290 Đường Láng, Phường Thịnh Quang, Q. Đống Đa, Hà Nội, Thịnh Quang, Đống Đa, Hà Nội",
  "email": "Ilovemylife.huong@gmail.com",
  "totalProduct": 0,
  "isNew": false,
  "isAutoOrderConfirmation": true,
  "rating": 3.9,
  "availableTime": {
    "openTime": "08:00",
    "closeTime": "23:30",
    "holidays": [
      {
        "name": "Tet Holiday",
        "startHolidayTime": "2022-01-29T17:00:00",
        "endHolidayTime": "2022-02-07T00:00:00"
      }
    ]
  },
  "warehouse": null,
  "warehouses": null,
  "createdTime": "0001-01-01T00:00:00",
  "isPublished": true,
  "note": null,
  "isF99Shop": null,
  "onStore": false,
  "totalVote": 26
}